LICENSE.md
README.md
setup.py
rstool/__init__.py
rstool/algorithms.py
rstool/const.py
rstool/headers.py
rstool/main.py
rstool/postprocess.py
rstool/prof.py
rstool.egg-info/PKG-INFO
rstool.egg-info/SOURCES.txt
rstool.egg-info/dependency_links.txt
rstool.egg-info/entry_points.txt
rstool.egg-info/requires.txt
rstool.egg-info/top_level.txt
rstool/drivers/__init__.py
rstool/drivers/default.py
rstool/drivers/imet.py
rstool/drivers/surf.py
rstool/drivers/template.py
rstool/drivers/ws.py