Metadata-Version: 2.1
Name: rstool
Version: 2.0.0
Summary: Command-line program for converting radiosonde measurement data to NetCDF and calculation of derived physical quantities, supporting InterMet Systems (iMet) and Windsond radiosondes, as well as calculating derived quantities from model profiles.
Home-page: https://github.com/peterkuma/rstool
Author: Peter Kuma
Author-email: peter@peterkuma.net
Keywords: atmospheric-scienceclimate,climate-model,climate-science,imet,intermet,netcdf,nwp,radiosonde,weather,weather-model,weather-balloon,windsond
Platform: any
Classifier: Development Status :: 5 - Production/Stable
Classifier: Environment :: Console
Classifier: Intended Audience :: Science/Research
Classifier: License :: OSI Approved :: MIT License
Classifier: Operating System :: OS Independent
Classifier: Programming Language :: Python :: 3
Classifier: Topic :: Scientific/Engineering
Classifier: Topic :: Scientific/Engineering :: Atmospheric Science
Classifier: Topic :: Scientific/Engineering :: Physics
License-File: LICENSE.md
